ig2wp/__init__.py
ig2wp/__main__.py
ig2wp/ig2wp.py
ig2wp/structures.py
ig2wp-0.1.0.dist-info/AUTHORS.md
ig2wp-0.1.0.dist-info/LICENSE
ig2wp-0.1.0.dist-info/METADATA
ig2wp-0.1.0.dist-info/WHEEL
ig2wp-0.1.0.dist-info/entry_points.txt
ig2wp-0.1.0.dist-info/top_level.txt
ig2wp-0.1.0.dist-info/RECORD
