Metadata-Version: 2.1
Name: ig2wp
Version: 0.1.0
Summary: Upload posts from Instagram to Wordpress using Instaloader Tool
Home-page: https://github.com/aderbique/ig2wp
Author: Austin Derbique
Author-email: austin@derbique.us
License: MIT
Keywords: instagram,wordpress,wordpress-uploader,instagram-post,instagram-wordpress,videos,photos,pictures,instagram-user-photos,instagram-photos,instagram-metadata,instagram-downloader
Platform: UNKNOWN
Classifier: Development Status :: 5 - Production/Stable
Classifier: Environment :: Console
Classifier: Intended Audience :: End Users/Desktop
Classifier: Intended Audience :: Developers
Classifier: License :: OSI Approved :: MIT License
Classifier: Operating System :: OS Independent
Classifier: Programming Language :: Python :: 3.6
Classifier: Programming Language :: Python :: 3.7
Classifier: Programming Language :: Python :: 3.8
Classifier: Programming Language :: Python :: 3.9
Classifier: Programming Language :: Python :: 3 :: Only
Classifier: Topic :: Internet
Classifier: Topic :: Multimedia :: Graphics
Requires-Python: >=3.6
License-File: LICENSE
License-File: AUTHORS.md
Requires-Dist: requests (>=2.4)
